meteociel/__init__.py
meteociel/__main__.py
meteociel/cities.py
meteociel/cli.py
meteociel/forecasts.py
meteociel/soundings.py
meteociel/stations.py
meteociel/utils.py
meteociel_api-1.1.2.dist-info/LICENSE
meteociel_api-1.1.2.dist-info/METADATA
meteociel_api-1.1.2.dist-info/WHEEL
meteociel_api-1.1.2.dist-info/entry_points.txt
meteociel_api-1.1.2.dist-info/top_level.txt
meteociel_api-1.1.2.dist-info/RECORD
