Metadata-Version: 2.1
Name: meteociel-api
Version: 1.1.2
Summary: An unofficial API for the Météociel website
Author: Gabriel HAUSKNOST, Antoine ROYER
Project-URL: Homepage, https://github.com/Meteo-API/meteociel_api
Project-URL: Documentation, http://meteociel-api.rtfd.io/
Classifier: Programming Language :: Python :: 3
Classifier: License :: OSI Approved :: GNU General Public License v3 or later (GPLv3+)
Classifier: Development Status :: 4 - Beta
Requires-Python: >=3.7
License-File: LICENSE
Requires-Dist: bs4
Requires-Dist: click
Requires-Dist: datetime
Requires-Dist: html5lib
Requires-Dist: numpy
Requires-Dist: pandas
Requires-Dist: requests
Provides-Extra: doc
Requires-Dist: sphinx >=7.0.1 ; extra == 'doc'
Requires-Dist: sphinx-rtd-theme ; extra == 'doc'
Requires-Dist: sphinx-autodocgen ; extra == 'doc'
